labelled_topic_clustering/__init__.py
labelled_topic_clustering/src/__init__.py
labelled_topic_clustering/src/embeddings.py
labelled_topic_clustering/src/helpers.py
labelled_topic_clustering/src/labelled_topic_clustering.py
labelled_topic_clustering/src/labels.py
labelled_topic_clustering/src/tokenizer.py
labelled_topic_clustering-1.1.0.dist-info/LICENSE
labelled_topic_clustering-1.1.0.dist-info/METADATA
labelled_topic_clustering-1.1.0.dist-info/WHEEL
labelled_topic_clustering-1.1.0.dist-info/top_level.txt
labelled_topic_clustering-1.1.0.dist-info/RECORD
