Metadata-Version: 2.1
Name: labelled-topic-clustering
Version: 1.1.0
Summary: Super Simple Labelled Topic Clustering
Home-page: https://github.com/tomhaydn/labelled-topic-clustering
Author: Tom Haydn
License: MIT
Keywords: Sentence,Topic,Clustering,Labelling,Cosine Similarity,LDA,HuggingFace,pyTorch,Spacy,NLP,Deep Learning
Platform: UNKNOWN
Classifier: License :: OSI Approved :: MIT License
Classifier: Programming Language :: Python :: 3.9
Classifier: Operating System :: OS Independent
Classifier: Development Status :: 5 - Production/Stable
Classifier: Natural Language :: English
Requires-Python: >=3.9
License-File: LICENSE
Requires-Dist: sentence-transformers ==2.2.2
Requires-Dist: gensim ==4.3.0
Requires-Dist: spacy ==3.5.3
Provides-Extra: dev
Requires-Dist: pytest >=7.0 ; extra == 'dev'
Requires-Dist: twine >=5.0.1 ; extra == 'dev'
Requires-Dist: pylint >=3.2.3 ; extra == 'dev'
